pycvutils-0.1.6.dist-info/METADATA
pycvutils-0.1.6.dist-info/WHEEL
pycvutils-0.1.6.dist-info/entry_points.txt
pycvutils-0.1.6.dist-info/licenses/LICENSE
pycvutils/__init__.py
pycvutils/blobs.py
pycvutils/brightness.py
pycvutils/channels.py
pycvutils/convert.py
pycvutils/coords.py
pycvutils/filling.py
pycvutils/matching.py
pycvutils/padding.py
pycvutils/resizing/__init__.py
pycvutils/resizing/by_ratio.py
pycvutils/resizing/normal.py
pycvutils/show.py
pycvutils/threshold.py
pycvutils-0.1.6.dist-info/RECORD
