Metadata-Version: 2.1
Name: PyCVutils
Version: 0.1.6
Summary: A bunch of useful wrappers around opencv-python library
Author-Email: SEBROVATER <sebrovskiy.k@gmail.com>
License: Apache-2.0
Project-URL: github, https://github.com/SEBROVATER/PyCVutils
Requires-Python: >=3.10
Requires-Dist: numpy>=1.22.0
Provides-Extra: contrib
Requires-Dist: opencv-contrib-python>=4.7.0.71; extra == "contrib"
Provides-Extra: contrib-headless
Requires-Dist: opencv-contrib-python-headless>=4.7.0.71; extra == "contrib-headless"
Provides-Extra: opencv
Requires-Dist: opencv-python>=4.7.0.71; extra == "opencv"
Provides-Extra: headless
Requires-Dist: opencv-python-headless>=4.7.0.71; extra == "headless"
